hirelucasforcanonical/__init__.py
hirelucasforcanonical/main.py
hirelucasforcanonical-0.1.1.dist-info/METADATA
hirelucasforcanonical-0.1.1.dist-info/WHEEL
hirelucasforcanonical-0.1.1.dist-info/entry_points.txt
hirelucasforcanonical-0.1.1.dist-info/RECORD
