Metadata-Version: 2.1
Name: hirelucasforcanonical
Version: 0.1.1
Summary: this is a package to practice packaging and CLI tool with python
Author: Lucas Gameiro Borges
Author-email: lucasgameirob@gmail.com
Requires-Python: >=3.8,<=3.12
Classifier: Programming Language :: Python :: 3
Classifier: Programming Language :: Python :: 3.8
Classifier: Programming Language :: Python :: 3.9
Classifier: Programming Language :: Python :: 3.10
Classifier: Programming Language :: Python :: 3.11
Requires-Dist: black (>=23.9.1,<24.0.0)
Requires-Dist: typer (>=0.9.0,<0.10.0)
